{"Req":{"jsonrpc":"2.0","method":"trace_replayTransaction","params":["0x4fd522e4da49c67287de93f2130ab41c31870b400bc66f7734a9d2a5e3a14a63",["stateDiff"]],"id":"114514"},"Rsp":{"jsonrpc":"2.0","id":"114514","result":{"output":"0x","stateDiff":{"0x7c125c1d515b8945841b3d5144a060115c58725f":{"balance":{"*":{"from":"0x9097ccc4950337298","to":"0x907be95d292814013"}},"code":"=","nonce":{"*":{"from":"0xf3d4d","to":"0xf3d4e"}},"storage":{}},"0x99084137ae36425c063b51712aabf5674a708587":{"balance":{"*":{"from":"0x8fc1c1c05f25c0","to":"0x248ebcb149e550d"}},"code":"=","nonce":"=","storage":{}},"0xf36f155486299ecaff2d4f5160ed5114c1f66000":{"balance":{"*":{"from":"0x406cad12e1a06c430c6b","to":"0x406cad14c68e98cc9d13"}},"code":"=","nonce":"=","storage":{}}},"trace":[],"vmTrace":null}}}
