{"Req":{"jsonrpc":"2.0","method":"trace_replayTransaction","params":["0x1a117f8001a1ba2e9539aa18ac0a3b99db67f1ffb5c7ad7133daea7bf2afec53",["stateDiff"]],"id":"114514"},"Rsp":{"jsonrpc":"2.0","id":"114514","result":{"output":"0x","stateDiff":{"0x28750c800bc46c1e731c2ebddd7857d3ffdf6971":{"balance":{"*":{"from":"0x6397ab89e65001e","to":"0x7ca606bd73f4e1e"}},"code":"=","nonce":"=","storage":{}},"0x6cc9397c3b38739dacbfaa68ead5f5d77ba5f455":{"balance":{"*":{"from":"0x24bd945f54d312382d","to":"0x24bc002724b732abbd"}},"code":"=","nonce":{"*":{"from":"0xca86b","to":"0xca86c"}},"storage":{}},"0x8f614cdb61e37b6f18d9705942c93fa86b04d711":{"balance":{"*":{"from":"0x8e9230f1cd4634cf6","to":"0x8e923354fb777ecf6"}},"code":"=","nonce":"=","storage":{}}},"trace":[],"vmTrace":null}}}
