{"Req":{"jsonrpc":"2.0","method":"trace_replayTransaction","params":["0xbe3d83136d9466884588b5f3ce7968f0ac7f00e9a1d2271661f759e31e36ad8e",["stateDiff"]],"id":"114514"},"Rsp":{"jsonrpc":"2.0","id":"114514","result":{"output":"0x","stateDiff":{"0x4c1471e1a6446534923164a132f825341c2cc446":{"balance":{"*":{"from":"0x1965aff261e7054","to":"0x19cb34fe41c49c4"}},"code":"=","nonce":"=","storage":{}},"0xc9af69904b4ba7f0fb69ab1a8719bd8950265e73":{"balance":{"*":{"from":"0x6090db2b280ae0c70d","to":"0x60901ff5cc471763cd"}},"code":"=","nonce":{"*":{"from":"0x504a3","to":"0x504a4"}},"storage":{}},"0xe25b7bad45c7738a697be20b4a812cacae7fbb91":{"balance":{"*":{"from":"0x85cabbbc40c9b30","to":"0x90e4e77f2d19b30"}},"code":"=","nonce":"=","storage":{}}},"trace":[],"vmTrace":null}}}
