{"Req":{"jsonrpc":"2.0","method":"trace_replayTransaction","params":["0x234df666c5d7658c6fc3c3f46aaeff4598a3d356b452cfb2f5f6a20a40c4e690",["stateDiff"]],"id":"114514"},"Rsp":{"jsonrpc":"2.0","id":"114514","result":{"output":"0x","stateDiff":{"0x000095e79eac4d76aab57cb2c1f091d553b36ca0":{"balance":{"*":{"from":"0x3bffa81b4b5c7d15d6a","to":"0x3bffa81d2f973fa356a"}},"code":"=","nonce":"=","storage":{}},"0x72ec7a020c613ca5c524d4665792180ae6cd7e41":{"balance":{"*":{"from":"0x295b5620cd2ca78","to":"0x263f2623c48bfb0"}},"code":"=","nonce":{"*":{"from":"0x8","to":"0x9"}},"storage":{}},"0x7c125c1d515b8945841b3d5144a060115c58725f":{"balance":{"*":{"from":"0x90bc7b55b7008d55c","to":"0x90bf5e4c9ce1d555c"}},"code":"=","nonce":"=","storage":{}}},"trace":[],"vmTrace":null}}}
